sslh/SSLH_database.py
sslh/SSLH_files.py
sslh/SSLH_inference.py
sslh/SSLH_utils.py
sslh/__init__.py
sslh-0.1.0.dist-info/DESCRIPTION.rst
sslh-0.1.0.dist-info/METADATA
sslh-0.1.0.dist-info/RECORD
sslh-0.1.0.dist-info/WHEEL
sslh-0.1.0.dist-info/metadata.json
sslh-0.1.0.dist-info/top_level.txt
