Metadata-Version: 2.0
Name: sslh
Version: 0.1.0
Summary: Techniques for Semi-Supervised Learning with Heterophily
Home-page: http://github.com/sslh/sslh/
Author: Wolfgang Gatterbauer
Author-email: gatt@cmu.edu
License: Apache Software License
Keywords: learning,belief propagation,classification
Platform: UNKNOWN
Classifier: Development Status :: 3 - Alpha
Classifier: Intended Audience :: Developers
Classifier: Natural Language :: English
Classifier: License :: OSI Approved :: Apache Software License
Classifier: Operating System :: OS Independent
Classifier: Programming Language :: Python
Classifier: Programming Language :: Python :: 2
Classifier: Programming Language :: Python :: 2.6
Classifier: Programming Language :: Python :: 2.7
Classifier: Programming Language :: SQL
Classifier: Topic :: Software Development :: Libraries :: Python Modules
Classifier: Topic :: Scientific/Engineering
Requires-Dist: numpy (>=1.9.1)
Requires-Dist: psycopg2 (>=2.5.4)
Requires-Dist: pyamg (>=2.2.1)
Requires-Dist: pytest (>=2.8.0)
Requires-Dist: scipy (>=0.15.1)
Requires-Dist: sklearn
